classifierpromax/ClassifierOptimizer.py
classifierpromax/ClassifierTrainer.py
classifierpromax/FeatureSelector.py
classifierpromax/ResultHandler.py
classifierpromax/__init__.py
classifierpromax-1.2.3.dist-info/LICENSE
classifierpromax-1.2.3.dist-info/METADATA
classifierpromax-1.2.3.dist-info/WHEEL
classifierpromax-1.2.3.dist-info/RECORD
