Metadata-Version: 2.3
Name: classifierpromax
Version: 1.2.3
Summary: Help you train and optimize many popular classifiers in one place with a summary table
License: MIT
Author: Long Nguyen, Jenson Chang, Gunisha Kaur, Han Wang
Requires-Python: >=3.12,<4.0
Classifier: License :: OSI Approved :: MIT License
Classifier: Programming Language :: Python :: 3
Classifier: Programming Language :: Python :: 3.12
Classifier: Programming Language :: Python :: 3.13
Requires-Dist: pandas (>=2.2.3,<3.0.0)
Requires-Dist: scikit-learn (>=1.6.1,<2.0.0)
